clip/__init__.py
clip/bpe_simple_vocab_16e6.txt.gz
clip/clip.py
clip/model.py
clip/simple_tokenizer.py
clip_openai-1.0.post20230121.dist-info/LICENSE
clip_openai-1.0.post20230121.dist-info/METADATA
clip_openai-1.0.post20230121.dist-info/WHEEL
clip_openai-1.0.post20230121.dist-info/top_level.txt
clip_openai-1.0.post20230121.dist-info/RECORD
