Metadata-Version: 2.1
Name: clip-openai
Version: 1.0.post20230121
Summary: CLIP package of OpenAI
Home-page: https://github.com/openai/CLIP
Author: OpenAI
License-File: LICENSE
Requires-Dist: ftfy
Requires-Dist: regex
Requires-Dist: tqdm
Requires-Dist: torch
Requires-Dist: torchvision
Provides-Extra: dev
Requires-Dist: pytest ; extra == 'dev'
